simsoexp/__init__.py
simsoexp/clientapi/simsodb.py
simsoexp/clientapi/metrics_collector.py
simsoexp/clientapi/__init__.py
simsoexp/clientapi/api.py
simsoexp-1.0.3.dist-info/metadata.json
simsoexp-1.0.3.dist-info/DESCRIPTION.rst
simsoexp-1.0.3.dist-info/WHEEL
simsoexp-1.0.3.dist-info/RECORD
simsoexp-1.0.3.dist-info/top_level.txt
simsoexp-1.0.3.dist-info/METADATA
