Metadata-Version: 2.0
Name: simsoexp
Version: 1.0.3
Summary: Simso Experiment Plaform client API
Home-page: https://github.com/Scriptopathe/simso-exp
Author: Josue Alvaez
Author-email: josue.alvarez.dev@outlook.com
License: BSD 2-Clause
Keywords: simso
Platform: UNKNOWN
Classifier: Development Status :: 4 - Beta
Classifier: Intended Audience :: Developers
Classifier: Topic :: Software Development :: Libraries
Classifier: License :: OSI Approved :: BSD License
Classifier: Programming Language :: Python :: 3
Classifier: Programming Language :: Python :: 3.2
Classifier: Programming Language :: Python :: 3.3
Classifier: Programming Language :: Python :: 3.4
Requires-Dist: simso
Provides-Extra: test
Requires-Dist: coverage; extra == 'test'
Provides-Extra: dev
Requires-Dist: check-manifest; extra == 'dev'
